[{"type":"SceneTagged","value":{"sceneId":"unknown","tag":{"name":"Linux 6.2.0-1018-azure","type":"platform","platformName":"Linux","platformVersion":"6.2.0-1018-azure"},"timestamp":"2023-12-10T04:52:13.502Z"}},{"type":"SceneTagged","value":{"sceneId":"unknown","tag":{"name":"webkit 17.4","type":"browser","browserName":"webkit","browserVersion":"17.4"},"timestamp":"2023-12-10T04:52:13.618Z"}},{"type":"TaskStarts","value":{"activityId":"l8rickfmkru1kh9g4fy7ynul","details":{"name":"Alice starts with an empty todo list","location":{"column":37,"line":83,"path":"/home/runner/work/supreme-octo-rotary-phone/supreme-octo-rotary-phone/spec/recording-items.spec.ts"}},"sceneId":"unknown","timestamp":"2023-12-10T04:52:13.631Z"}},{"type":"InteractionStarts","value":{"activityId":"mgifdxhfjctakkechbuq84rk","details":{"name":"Alice navigates to '/'","location":{"column":18,"line":9,"path":"/home/runner/work/supreme-octo-rotary-phone/supreme-octo-rotary-phone/spec/todo-list-app/TodoApp/tasks.ts"}},"sceneId":"unknown","timestamp":"2023-12-10T04:52:13.632Z"}},{"type":"InteractionFinished","value":{"activityId":"mgifdxhfjctakkechbuq84rk","details":{"name":"Alice navigates to '/'","location":{"column":18,"line":9,"path":"/home/runner/work/supreme-octo-rotary-phone/supreme-octo-rotary-phone/spec/todo-list-app/TodoApp/tasks.ts"}},"outcome":{"code":64},"sceneId":"unknown","timestamp":"2023-12-10T04:52:13.962Z"}},{"type":"InteractionStarts","value":{"activityId":"qbrrg040pr2d5ordg0eisbar","details":{"name":"Alice ensures that website title does equal 'Serenity/JS TodoApp'","location":{"column":37,"line":83,"path":"/home/runner/work/supreme-octo-rotary-phone/supreme-octo-rotary-phone/spec/recording-items.spec.ts"}},"sceneId":"unknown","timestamp":"2023-12-10T04:52:13.973Z"}},{"type":"InteractionFinished","value":{"activityId":"qbrrg040pr2d5ordg0eisbar","details":{"name":"Alice ensures that website title does equal 'Serenity/JS TodoApp'","location":{"column":37,"line":83,"path":"/home/runner/work/supreme-octo-rotary-phone/supreme-octo-rotary-phone/spec/recording-items.spec.ts"}},"outcome":{"code":64},"sceneId":"unknown","timestamp":"2023-12-10T04:52:13.977Z"}},{"type":"TaskFinished","value":{"activityId":"l8rickfmkru1kh9g4fy7ynul","details":{"name":"Alice starts with an empty todo list","location":{"column":37,"line":83,"path":"/home/runner/work/supreme-octo-rotary-phone/supreme-octo-rotary-phone/spec/recording-items.spec.ts"}},"outcome":{"code":64},"sceneId":"unknown","timestamp":"2023-12-10T04:52:13.987Z"}},{"type":"InteractionStarts","value":{"activityId":"aebr8nbaifln07iofnl64y7y","details":{"name":"Alice ensures that main section does not become present","location":{"column":24,"line":85,"path":"/home/runner/work/supreme-octo-rotary-phone/supreme-octo-rotary-phone/spec/recording-items.spec.ts"}},"sceneId":"unknown","timestamp":"2023-12-10T04:52:13.998Z"}},{"type":"InteractionFinished","value":{"activityId":"aebr8nbaifln07iofnl64y7y","details":{"name":"Alice ensures that main section does not become present","location":{"column":24,"line":85,"path":"/home/runner/work/supreme-octo-rotary-phone/supreme-octo-rotary-phone/spec/recording-items.spec.ts"}},"outcome":{"code":64},"sceneId":"unknown","timestamp":"2023-12-10T04:52:14.252Z"}},{"type":"InteractionStarts","value":{"activityId":"g498wwdhmp99tc7epte36gsc","details":{"name":"Alice ensures that footer section does not become present","location":{"column":24,"line":86,"path":"/home/runner/work/supreme-octo-rotary-phone/supreme-octo-rotary-phone/spec/recording-items.spec.ts"}},"sceneId":"unknown","timestamp":"2023-12-10T04:52:14.263Z"}},{"type":"InteractionFinished","value":{"activityId":"g498wwdhmp99tc7epte36gsc","details":{"name":"Alice ensures that footer section does not become present","location":{"column":24,"line":86,"path":"/home/runner/work/supreme-octo-rotary-phone/supreme-octo-rotary-phone/spec/recording-items.spec.ts"}},"outcome":{"code":64},"sceneId":"unknown","timestamp":"2023-12-10T04:52:14.515Z"}},{"type":"TaskStarts","value":{"activityId":"fcu4oravrx4lmoa79dl4o92e","details":{"name":"Alice records an item called 'buy some cheese'","location":{"column":27,"line":88,"path":"/home/runner/work/supreme-octo-rotary-phone/supreme-octo-rotary-phone/spec/recording-items.spec.ts"}},"sceneId":"unknown","timestamp":"2023-12-10T04:52:14.526Z"}},{"type":"InteractionStarts","value":{"activityId":"crn15gv1q5ea1jj49cltcwo3","details":{"name":"Alice enters 'buy some cheese' into \"What needs to be done?\" input box","location":{"column":30,"line":12,"path":"/home/runner/work/supreme-octo-rotary-phone/supreme-octo-rotary-phone/spec/todo-list-app/TodoItem/tasks.ts"}},"sceneId":"unknown","timestamp":"2023-12-10T04:52:14.527Z"}},{"type":"InteractionFinished","value":{"activityId":"crn15gv1q5ea1jj49cltcwo3","details":{"name":"Alice enters 'buy some cheese' into \"What needs to be done?\" input box","location":{"column":30,"line":12,"path":"/home/runner/work/supreme-octo-rotary-phone/supreme-octo-rotary-phone/spec/todo-list-app/TodoItem/tasks.ts"}},"outcome":{"code":64},"sceneId":"unknown","timestamp":"2023-12-10T04:52:14.543Z"}},{"type":"InteractionStarts","value":{"activityId":"qqkajmlsva550k0bh3dgfdt2","details":{"name":"Alice presses key Enter in \"What needs to be done?\" input box","location":{"column":32,"line":13,"path":"/home/runner/work/supreme-octo-rotary-phone/supreme-octo-rotary-phone/spec/todo-list-app/TodoItem/tasks.ts"}},"sceneId":"unknown","timestamp":"2023-12-10T04:52:14.555Z"}},{"type":"InteractionFinished","value":{"activityId":"qqkajmlsva550k0bh3dgfdt2","details":{"name":"Alice presses key Enter in \"What needs to be done?\" input box","location":{"column":32,"line":13,"path":"/home/runner/work/supreme-octo-rotary-phone/supreme-octo-rotary-phone/spec/todo-list-app/TodoItem/tasks.ts"}},"outcome":{"code":64},"sceneId":"unknown","timestamp":"2023-12-10T04:52:14.607Z"}},{"type":"InteractionStarts","value":{"activityId":"edgtjmy5xukgju82l8f5fq5a","details":{"name":"Alice waits until displayed items does contain 'buy some cheese'","location":{"column":14,"line":14,"path":"/home/runner/work/supreme-octo-rotary-phone/supreme-octo-rotary-phone/spec/todo-list-app/TodoItem/tasks.ts"}},"sceneId":"unknown","timestamp":"2023-12-10T04:52:14.618Z"}},{"type":"InteractionFinished","value":{"activityId":"edgtjmy5xukgju82l8f5fq5a","details":{"name":"Alice waits until displayed items does contain 'buy some cheese'","location":{"column":14,"line":14,"path":"/home/runner/work/supreme-octo-rotary-phone/supreme-octo-rotary-phone/spec/todo-list-app/TodoItem/tasks.ts"}},"outcome":{"code":64},"sceneId":"unknown","timestamp":"2023-12-10T04:52:14.648Z"}},{"type":"TaskFinished","value":{"activityId":"fcu4oravrx4lmoa79dl4o92e","details":{"name":"Alice records an item called 'buy some cheese'","location":{"column":27,"line":88,"path":"/home/runner/work/supreme-octo-rotary-phone/supreme-octo-rotary-phone/spec/recording-items.spec.ts"}},"outcome":{"code":64},"sceneId":"unknown","timestamp":"2023-12-10T04:52:14.661Z"}},{"type":"InteractionStarts","value":{"activityId":"lt78clqssqrx8gv63wxbxgjn","details":{"name":"Alice ensures that main section does become visible","location":{"column":24,"line":90,"path":"/home/runner/work/supreme-octo-rotary-phone/supreme-octo-rotary-phone/spec/recording-items.spec.ts"}},"sceneId":"unknown","timestamp":"2023-12-10T04:52:14.673Z"}},{"type":"InteractionFinished","value":{"activityId":"lt78clqssqrx8gv63wxbxgjn","details":{"name":"Alice ensures that main section does become visible","location":{"column":24,"line":90,"path":"/home/runner/work/supreme-octo-rotary-phone/supreme-octo-rotary-phone/spec/recording-items.spec.ts"}},"outcome":{"code":64},"sceneId":"unknown","timestamp":"2023-12-10T04:52:14.705Z"}},{"type":"InteractionStarts","value":{"activityId":"cythqfq3bb15pir4jri71fvi","details":{"name":"Alice ensures that footer section does become visible","location":{"column":24,"line":91,"path":"/home/runner/work/supreme-octo-rotary-phone/supreme-octo-rotary-phone/spec/recording-items.spec.ts"}},"sceneId":"unknown","timestamp":"2023-12-10T04:52:14.715Z"}},{"type":"InteractionFinished","value":{"activityId":"cythqfq3bb15pir4jri71fvi","details":{"name":"Alice ensures that footer section does become visible","location":{"column":24,"line":91,"path":"/home/runner/work/supreme-octo-rotary-phone/supreme-octo-rotary-phone/spec/recording-items.spec.ts"}},"outcome":{"code":64},"sceneId":"unknown","timestamp":"2023-12-10T04:52:14.731Z"}},{"type":"SceneFinishes","value":{"sceneId":"unknown","timestamp":"2023-12-10T04:52:14.742Z"}},{"type":"AsyncOperationAttempted","value":{"correlationId":"cwp2sfsnym3tommz9h716f68","description":"Dismissing Alice...","name":"Stage","timestamp":"2023-12-10T04:52:14.753Z"}},{"type":"AsyncOperationCompleted","value":{"correlationId":"cwp2sfsnym3tommz9h716f68","timestamp":"2023-12-10T04:52:14.753Z"}}]