[{"type":"SceneTagged","value":{"sceneId":"unknown","tag":{"name":"Linux 6.2.0-1018-azure","type":"platform","platformName":"Linux","platformVersion":"6.2.0-1018-azure"},"timestamp":"2023-12-10T07:47:03.625Z"}},{"type":"SceneTagged","value":{"sceneId":"unknown","tag":{"name":"firefox 119.0","type":"browser","browserName":"firefox","browserVersion":"119.0"},"timestamp":"2023-12-10T07:47:03.775Z"}},{"type":"TaskStarts","value":{"activityId":"yzz6jajinhlumr4s1hnqbdru","details":{"name":"Alice starts with an empty todo list","location":{"column":37,"line":61,"path":"/home/runner/work/supreme-octo-rotary-phone/supreme-octo-rotary-phone/spec/recording-items.spec.ts"}},"sceneId":"unknown","timestamp":"2023-12-10T07:47:03.788Z"}},{"type":"InteractionStarts","value":{"activityId":"n24xd7wql2lwdfdmaan62x82","details":{"name":"Alice navigates to '/'","location":{"column":18,"line":9,"path":"/home/runner/work/supreme-octo-rotary-phone/supreme-octo-rotary-phone/spec/todo-list-app/TodoApp/tasks.ts"}},"sceneId":"unknown","timestamp":"2023-12-10T07:47:03.789Z"}},{"type":"InteractionFinished","value":{"activityId":"n24xd7wql2lwdfdmaan62x82","details":{"name":"Alice navigates to '/'","location":{"column":18,"line":9,"path":"/home/runner/work/supreme-octo-rotary-phone/supreme-octo-rotary-phone/spec/todo-list-app/TodoApp/tasks.ts"}},"outcome":{"code":64},"sceneId":"unknown","timestamp":"2023-12-10T07:47:03.913Z"}},{"type":"InteractionStarts","value":{"activityId":"n491f2yr7u6qvkpjzrgazgdb","details":{"name":"Alice ensures that website title does equal 'Serenity/JS TodoApp'","location":{"column":37,"line":61,"path":"/home/runner/work/supreme-octo-rotary-phone/supreme-octo-rotary-phone/spec/recording-items.spec.ts"}},"sceneId":"unknown","timestamp":"2023-12-10T07:47:03.924Z"}},{"type":"InteractionFinished","value":{"activityId":"n491f2yr7u6qvkpjzrgazgdb","details":{"name":"Alice ensures that website title does equal 'Serenity/JS TodoApp'","location":{"column":37,"line":61,"path":"/home/runner/work/supreme-octo-rotary-phone/supreme-octo-rotary-phone/spec/recording-items.spec.ts"}},"outcome":{"code":64},"sceneId":"unknown","timestamp":"2023-12-10T07:47:03.938Z"}},{"type":"TaskFinished","value":{"activityId":"yzz6jajinhlumr4s1hnqbdru","details":{"name":"Alice starts with an empty todo list","location":{"column":37,"line":61,"path":"/home/runner/work/supreme-octo-rotary-phone/supreme-octo-rotary-phone/spec/recording-items.spec.ts"}},"outcome":{"code":64},"sceneId":"unknown","timestamp":"2023-12-10T07:47:03.948Z"}},{"type":"TaskStarts","value":{"activityId":"yh379aemay20gyetur9xpco8","details":{"name":"Alice records an item called 'buy some cheese'","location":{"column":27,"line":63,"path":"/home/runner/work/supreme-octo-rotary-phone/supreme-octo-rotary-phone/spec/recording-items.spec.ts"}},"sceneId":"unknown","timestamp":"2023-12-10T07:47:03.960Z"}},{"type":"InteractionStarts","value":{"activityId":"s0q87toiq6chy9ez86p9885m","details":{"name":"Alice enters 'buy some cheese' into \"What needs to be done?\" input box","location":{"column":30,"line":12,"path":"/home/runner/work/supreme-octo-rotary-phone/supreme-octo-rotary-phone/spec/todo-list-app/TodoItem/tasks.ts"}},"sceneId":"unknown","timestamp":"2023-12-10T07:47:03.961Z"}},{"type":"InteractionFinished","value":{"activityId":"s0q87toiq6chy9ez86p9885m","details":{"name":"Alice enters 'buy some cheese' into \"What needs to be done?\" input box","location":{"column":30,"line":12,"path":"/home/runner/work/supreme-octo-rotary-phone/supreme-octo-rotary-phone/spec/todo-list-app/TodoItem/tasks.ts"}},"outcome":{"code":64},"sceneId":"unknown","timestamp":"2023-12-10T07:47:03.998Z"}},{"type":"InteractionStarts","value":{"activityId":"jmkbfwjyx5pltp5lkk6nrgcw","details":{"name":"Alice presses key Enter in \"What needs to be done?\" input box","location":{"column":32,"line":13,"path":"/home/runner/work/supreme-octo-rotary-phone/supreme-octo-rotary-phone/spec/todo-list-app/TodoItem/tasks.ts"}},"sceneId":"unknown","timestamp":"2023-12-10T07:47:04.009Z"}},{"type":"InteractionFinished","value":{"activityId":"jmkbfwjyx5pltp5lkk6nrgcw","details":{"name":"Alice presses key Enter in \"What needs to be done?\" input box","location":{"column":32,"line":13,"path":"/home/runner/work/supreme-octo-rotary-phone/supreme-octo-rotary-phone/spec/todo-list-app/TodoItem/tasks.ts"}},"outcome":{"code":64},"sceneId":"unknown","timestamp":"2023-12-10T07:47:04.044Z"}},{"type":"InteractionStarts","value":{"activityId":"mk26gvp8vu65dmpmh6h3z3qo","details":{"name":"Alice waits until displayed items does contain 'buy some cheese'","location":{"column":14,"line":14,"path":"/home/runner/work/supreme-octo-rotary-phone/supreme-octo-rotary-phone/spec/todo-list-app/TodoItem/tasks.ts"}},"sceneId":"unknown","timestamp":"2023-12-10T07:47:04.055Z"}},{"type":"InteractionFinished","value":{"activityId":"mk26gvp8vu65dmpmh6h3z3qo","details":{"name":"Alice waits until displayed items does contain 'buy some cheese'","location":{"column":14,"line":14,"path":"/home/runner/work/supreme-octo-rotary-phone/supreme-octo-rotary-phone/spec/todo-list-app/TodoItem/tasks.ts"}},"outcome":{"code":64},"sceneId":"unknown","timestamp":"2023-12-10T07:47:04.078Z"}},{"type":"TaskFinished","value":{"activityId":"yh379aemay20gyetur9xpco8","details":{"name":"Alice records an item called 'buy some cheese'","location":{"column":27,"line":63,"path":"/home/runner/work/supreme-octo-rotary-phone/supreme-octo-rotary-phone/spec/recording-items.spec.ts"}},"outcome":{"code":64},"sceneId":"unknown","timestamp":"2023-12-10T07:47:04.088Z"}},{"type":"InteractionStarts","value":{"activityId":"ycb80h8dh9ge13u7kmqxzp6p","details":{"name":"Alice ensures that the value of \"What needs to be done?\" input box does equal ''","location":{"column":24,"line":65,"path":"/home/runner/work/supreme-octo-rotary-phone/supreme-octo-rotary-phone/spec/recording-items.spec.ts"}},"sceneId":"unknown","timestamp":"2023-12-10T07:47:04.099Z"}},{"type":"InteractionFinished","value":{"activityId":"ycb80h8dh9ge13u7kmqxzp6p","details":{"name":"Alice ensures that the value of \"What needs to be done?\" input box does equal ''","location":{"column":24,"line":65,"path":"/home/runner/work/supreme-octo-rotary-phone/supreme-octo-rotary-phone/spec/recording-items.spec.ts"}},"outcome":{"code":64},"sceneId":"unknown","timestamp":"2023-12-10T07:47:04.103Z"}},{"type":"InteractionStarts","value":{"activityId":"nvgk2ic0f5mlnwa0y6rgmhvi","details":{"name":"Alice ensures that <<persisted item called buy some cheese>>.name does equal 'buy some cheese'","location":{"column":24,"line":67,"path":"/home/runner/work/supreme-octo-rotary-phone/supreme-octo-rotary-phone/spec/recording-items.spec.ts"}},"sceneId":"unknown","timestamp":"2023-12-10T07:47:04.114Z"}},{"type":"InteractionFinished","value":{"activityId":"nvgk2ic0f5mlnwa0y6rgmhvi","details":{"name":"Alice ensures that <<persisted item called buy some cheese>>.name does equal 'buy some cheese'","location":{"column":24,"line":67,"path":"/home/runner/work/supreme-octo-rotary-phone/supreme-octo-rotary-phone/spec/recording-items.spec.ts"}},"outcome":{"code":64},"sceneId":"unknown","timestamp":"2023-12-10T07:47:04.118Z"}},{"type":"InteractionStarts","value":{"activityId":"w826ibuvfndhjk369a95ewdw","details":{"name":"Alice ensures that <<persisted item called buy some cheese>>.completed does equal false","location":{"column":24,"line":68,"path":"/home/runner/work/supreme-octo-rotary-phone/supreme-octo-rotary-phone/spec/recording-items.spec.ts"}},"sceneId":"unknown","timestamp":"2023-12-10T07:47:04.128Z"}},{"type":"InteractionFinished","value":{"activityId":"w826ibuvfndhjk369a95ewdw","details":{"name":"Alice ensures that <<persisted item called buy some cheese>>.completed does equal false","location":{"column":24,"line":68,"path":"/home/runner/work/supreme-octo-rotary-phone/supreme-octo-rotary-phone/spec/recording-items.spec.ts"}},"outcome":{"code":64},"sceneId":"unknown","timestamp":"2023-12-10T07:47:04.131Z"}},{"type":"SceneFinishes","value":{"sceneId":"unknown","timestamp":"2023-12-10T07:47:04.141Z"}},{"type":"AsyncOperationAttempted","value":{"correlationId":"rep0wrg9av2af9ofnbkzu5sx","description":"Dismissing Alice...","name":"Stage","timestamp":"2023-12-10T07:47:04.152Z"}},{"type":"AsyncOperationCompleted","value":{"correlationId":"rep0wrg9av2af9ofnbkzu5sx","timestamp":"2023-12-10T07:47:04.152Z"}}]